Workbook

Sheet Assumptions
A1: TailWag
A2: Revenue Forecast — Assumptions | April–December 2026
B4: Apr | C4: May | D4: Jun | E4: Jul | F4: Aug | G4: Sep | H4: Oct | I4: Nov | J4: Dec
A5: CLIENT COUNTS
A6: New Strategic Partner Clients | B6: 15 | C6: 15 | D6: 5 | E6: 5 | F6: 5 | G6: 5 | H6: 5 | I6: 5 | J6: 5
A7: New Standard Clients ($249) | B7: 15 | C7: 15 | D7: 5 | E7: 5 | F7: 5 | G7: 5 | H7: 5 | I7: 5 | J7: 5
A8: Monthly Churn Rate | B8: 0.03 | C8: 0.03 | D8: 0.03 | E8: 0.03 | F8: 0.03 | G8: 0.03 | H8: 0.03 | I8: 0.03 | J8: 0.03
A9: Total Strategic Partner Clients | B9: =B6 -> 15 | C9: =ROUND(B9*(1-C8)+C6,0) -> 30 | D9: =ROUND(C9*(1-D8)+D6,0) -> 34 | E9: =ROUND(D9*(1-E8)+E6,0) -> 38 | F9: =ROUND(E9*(1-F8)+F6,0) -> 42 | G9: =ROUND(F9*(1-G8)+G6,0) -> 46 | H9: =ROUND(G9*(1-H8)+H6,0) -> 50 | I9: =ROUND(H9*(1-I8)+I6,0) -> 54 | J9: =ROUND(I9*(1-J8)+J6,0) -> 57
A10: Total Standard Clients ($249) | B10: =B7 -> 15 | C10: =ROUND(B10*(1-C8)+C7,0) -> 30 | D10: =ROUND(C10*(1-D8)+D7,0) -> 34 | E10: =ROUND(D10*(1-E8)+E7,0) -> 38 | F10: =ROUND(E10*(1-F8)+F7,0) -> 42 | G10: =ROUND(F10*(1-G8)+G7,0) -> 46 | H10: =ROUND(G10*(1-H8)+H7,0) -> 50 | I10: =ROUND(H10*(1-I8)+I7,0) -> 54 | J10: =ROUND(I10*(1-J8)+J7,0) -> 57
A11: Total Active Clients | B11: =B9+B10 -> 30 | C11: =C9+C10 -> 60 | D11: =D9+D10 -> 68 | E11: =E9+E10 -> 76 | F11: =F9+F10 -> 84 | G11: =G9+G10 -> 92 | H11: =H9+H10 -> 100 | I11: =I9+I10 -> 108 | J11: =J9+J10 -> 114
A12: PRICING
A13: Strategic Partner Monthly Price | B13: 159 | C13: 159 | D13: 159 | E13: 159 | F13: 159 | G13: 159 | H13: 159 | I13: 159 | J13: 159
A14: Standard Monthly Price | B14: 249 | C14: 249 | D14: 249 | E14: 249 | F14: 249 | G14: 249 | H14: 249 | I14: 249 | J14: 249
A15: COST ASSUMPTIONS (per client/mo)
A16: Twilio SMS Cost / Client | B16: 12 | C16: 12 | D16: 12 | E16: 12 | F16: 12 | G16: 12 | H16: 12 | I16: 12 | J16: 12
A17: Anthropic API Cost / Client | B17: 8 | C17: 8 | D17: 8 | E17: 8 | F17: 8 | G17: 8 | H17: 8 | I17: 8 | J17: 8
A18: FIXED MONTHLY EXPENSES
A19: Render Hosting | B19: 50 | C19: 50 | D19: 50 | E19: 50 | F19: 50 | G19: 50 | H19: 50 | I19: 50 | J19: 50
A20: Supabase | B20: 25 | C20: 25 | D20: 25 | E20: 25 | F20: 25 | G20: 25 | H20: 25 | I20: 25 | J20: 25
A21: Stripe Fees (2.9% + $0.30 est.) | B21: =ROUND('P&L'!B8*0.029,0) -> 177 | C21: =ROUND('P&L'!C8*0.029,0) -> 355 | D21: =ROUND('P&L'!D8*0.029,0) -> 402 | E21: =ROUND('P&L'!E8*0.029,0) -> 450 | F21: =ROUND('P&L'!F8*0.029,0) -> 497 | G21: =ROUND('P&L'!G8*0.029,0) -> 544 | H21: =ROUND('P&L'!H8*0.029,0) -> 592 | I21: =ROUND('P&L'!I8*0.029,0) -> 639 | J21: =ROUND('P&L'!J8*0.029,0) -> 674
A22: Brevo (Email Marketing) | B22: 25 | C22: 25 | D22: 25 | E22: 25 | F22: 25 | G22: 25 | H22: 25 | I22: 25 | J22: 25
A23: Domain & Tools | B23: 30 | C23: 30 | D23: 30 | E23: 30 | F23: 30 | G23: 30 | H23: 30 | I23: 30 | J23: 30
A24: Gas & Sales Expenses | B24: 200 | C24: 200 | D24: 200 | E24: 200 | F24: 200 | G24: 200 | H24: 200 | I24: 200 | J24: 200
A25: Insurance | B25: 100 | C25: 100 | D25: 100 | E25: 100 | F25: 100 | G25: 100 | H25: 100 | I25: 100 | J25: 100
A26: Green text = editable input. Change these to model different scenarios.

Sheet P&L
A1: TailWag
A2: Profit & Loss Forecast | April–December 2026
B4: Apr | C4: May | D4: Jun | E4: Jul | F4: Aug | G4: Sep | H4: Oct | I4: Nov | J4: Dec
A5: REVENUE
A6: Strategic Partner Revenue | B6: =Assumptions!B9*Assumptions!B13 -> 2385 | C6: =Assumptions!C9*Assumptions!C13 -> 4770 | D6: =Assumptions!D9*Assumptions!D13 -> 5406 | E6: =Assumptions!E9*Assumptions!E13 -> 6042 | F6: =Assumptions!F9*Assumptions!F13 -> 6678 | G6: =Assumptions!G9*Assumptions!G13 -> 7314 | H6: =Assumptions!H9*Assumptions!H13 -> 7950 | I6: =Assumptions!I9*Assumptions!I13 -> 8586 | J6: =Assumptions!J9*Assumptions!J13 -> 9063
A7: Standard ($249) Revenue | B7: =Assumptions!B10*Assumptions!B14 -> 3735 | C7: =Assumptions!C10*Assumptions!C14 -> 7470 | D7: =Assumptions!D10*Assumptions!D14 -> 8466 | E7: =Assumptions!E10*Assumptions!E14 -> 9462 | F7: =Assumptions!F10*Assumptions!F14 -> 10458 | G7: =Assumptions!G10*Assumptions!G14 -> 11454 | H7: =Assumptions!H10*Assumptions!H14 -> 12450 | I7: =Assumptions!I10*Assumptions!I14 -> 13446 | J7: =Assumptions!J10*Assumptions!J14 -> 14193
A8: Total Revenue | B8: =B6+B7 -> 6120 | C8: =C6+C7 -> 12240 | D8: =D6+D7 -> 13872 | E8: =E6+E7 -> 15504 | F8: =F6+F7 -> 17136 | G8: =G6+G7 -> 18768 | H8: =H6+H7 -> 20400 | I8: =I6+I7 -> 22032 | J8: =J6+J7 -> 23256
A9: COST OF GOODS SOLD
A10: Twilio SMS Costs | B10: =Assumptions!B11*Assumptions!B16 -> 360 | C10: =Assumptions!C11*Assumptions!C16 -> 720 | D10: =Assumptions!D11*Assumptions!D16 -> 816 | E10: =Assumptions!E11*Assumptions!E16 -> 912 | F10: =Assumptions!F11*Assumptions!F16 -> 1008 | G10: =Assumptions!G11*Assumptions!G16 -> 1104 | H10: =Assumptions!H11*Assumptions!H16 -> 1200 | I10: =Assumptions!I11*Assumptions!I16 -> 1296 | J10: =Assumptions!J11*Assumptions!J16 -> 1368
A11: Anthropic API Costs | B11: =Assumptions!B11*Assumptions!B17 -> 240 | C11: =Assumptions!C11*Assumptions!C17 -> 480 | D11: =Assumptions!D11*Assumptions!D17 -> 544 | E11: =Assumptions!E11*Assumptions!E17 -> 608 | F11: =Assumptions!F11*Assumptions!F17 -> 672 | G11: =Assumptions!G11*Assumptions!G17 -> 736 | H11: =Assumptions!H11*Assumptions!H17 -> 800 | I11: =Assumptions!I11*Assumptions!I17 -> 864 | J11: =Assumptions!J11*Assumptions!J17 -> 912
A12: Total COGS | B12: =B10+B11 -> 600 | C12: =C10+C11 -> 1200 | D12: =D10+D11 -> 1360 | E12: =E10+E11 -> 1520 | F12: =F10+F11 -> 1680 | G12: =G10+G11 -> 1840 | H12: =H10+H11 -> 2000 | I12: =I10+I11 -> 2160 | J12: =J10+J11 -> 2280
A13: Gross Profit | B13: =B8-B12 -> 5520 | C13: =C8-C12 -> 11040 | D13: =D8-D12 -> 12512 | E13: =E8-E12 -> 13984 | F13: =F8-F12 -> 15456 | G13: =G8-G12 -> 16928 | H13: =H8-H12 -> 18400 | I13: =I8-I12 -> 19872 | J13: =J8-J12 -> 20976
A14: Gross Margin % | B14: =IF(B8=0,0,B13/B8) -> 0.90196078 | C14: =IF(C8=0,0,C13/C8) -> 0.90196078 | D14: =IF(D8=0,0,D13/D8) -> 0.90196078 | E14: =IF(E8=0,0,E13/E8) -> 0.90196078 | F14: =IF(F8=0,0,F13/F8) -> 0.90196078 | G14: =IF(G8=0,0,G13/G8) -> 0.90196078 | H14: =IF(H8=0,0,H13/H8) -> 0.90196078 | I14: =IF(I8=0,0,I13/I8) -> 0.90196078 | J14: =IF(J8=0,0,J13/J8) -> 0.90196078
A15: OPERATING EXPENSES
A16: Render Hosting | B16: =Assumptions!B19 -> 50 | C16: =Assumptions!C19 -> 50 | D16: =Assumptions!D19 -> 50 | E16: =Assumptions!E19 -> 50 | F16: =Assumptions!F19 -> 50 | G16: =Assumptions!G19 -> 50 | H16: =Assumptions!H19 -> 50 | I16: =Assumptions!I19 -> 50 | J16: =Assumptions!J19 -> 50
A17: Supabase | B17: =Assumptions!B20 -> 25 | C17: =Assumptions!C20 -> 25 | D17: =Assumptions!D20 -> 25 | E17: =Assumptions!E20 -> 25 | F17: =Assumptions!F20 -> 25 | G17: =Assumptions!G20 -> 25 | H17: =Assumptions!H20 -> 25 | I17: =Assumptions!I20 -> 25 | J17: =Assumptions!J20 -> 25
A18: Stripe Processing Fees | B18: =Assumptions!B21 -> 177 | C18: =Assumptions!C21 -> 355 | D18: =Assumptions!D21 -> 402 | E18: =Assumptions!E21 -> 450 | F18: =Assumptions!F21 -> 497 | G18: =Assumptions!G21 -> 544 | H18: =Assumptions!H21 -> 592 | I18: =Assumptions!I21 -> 639 | J18: =Assumptions!J21 -> 674
A19: Brevo (Email Marketing) | B19: =Assumptions!B22 -> 25 | C19: =Assumptions!C22 -> 25 | D19: =Assumptions!D22 -> 25 | E19: =Assumptions!E22 -> 25 | F19: =Assumptions!F22 -> 25 | G19: =Assumptions!G22 -> 25 | H19: =Assumptions!H22 -> 25 | I19: =Assumptions!I22 -> 25 | J19: =Assumptions!J22 -> 25
A20: Domain & Tools | B20: =Assumptions!B23 -> 30 | C20: =Assumptions!C23 -> 30 | D20: =Assumptions!D23 -> 30 | E20: =Assumptions!E23 -> 30 | F20: =Assumptions!F23 -> 30 | G20: =Assumptions!G23 -> 30 | H20: =Assumptions!H23 -> 30 | I20: =Assumptions!I23 -> 30 | J20: =Assumptions!J23 -> 30
A21: Gas & Sales Expenses | B21: =Assumptions!B24 -> 200 | C21: =Assumptions!C24 -> 200 | D21: =Assumptions!D24 -> 200 | E21: =Assumptions!E24 -> 200 | F21: =Assumptions!F24 -> 200 | G21: =Assumptions!G24 -> 200 | H21: =Assumptions!H24 -> 200 | I21: =Assumptions!I24 -> 200 | J21: =Assumptions!J24 -> 200
A22: Insurance | B22: =Assumptions!B25 -> 100 | C22: =Assumptions!C25 -> 100 | D22: =Assumptions!D25 -> 100 | E22: =Assumptions!E25 -> 100 | F22: =Assumptions!F25 -> 100 | G22: =Assumptions!G25 -> 100 | H22: =Assumptions!H25 -> 100 | I22: =Assumptions!I25 -> 100 | J22: =Assumptions!J25 -> 100
A23: Total Operating Expenses | B23: =SUM(B16:B22) -> 607 | C23: =SUM(C16:C22) -> 785 | D23: =SUM(D16:D22) -> 832 | E23: =SUM(E16:E22) -> 880 | F23: =SUM(F16:F22) -> 927 | G23: =SUM(G16:G22) -> 974 | H23: =SUM(H16:H22) -> 1022 | I23: =SUM(I16:I22) -> 1069 | J23: =SUM(J16:J22) -> 1104
A24: EBITDA / Net Income | B24: =B13-B23 -> 4913 | C24: =C13-C23 -> 10255 | D24: =D13-D23 -> 11680 | E24: =E13-E23 -> 13104 | F24: =F13-F23 -> 14529 | G24: =G13-G23 -> 15954 | H24: =H13-H23 -> 17378 | I24: =I13-I23 -> 18803 | J24: =J13-J23 -> 19872
A25: Net Margin % | B25: =IF(B8=0,0,B24/B8) -> 0.80277778 | C25: =IF(C8=0,0,C24/C8) -> 0.8378268 | D25: =IF(D8=0,0,D24/D8) -> 0.84198385 | E25: =IF(E8=0,0,E24/E8) -> 0.84520124 | F25: =IF(F8=0,0,F24/F8) -> 0.84786415 | G25: =IF(G8=0,0,G24/G8) -> 0.85006394 | H25: =IF(H8=0,0,H24/H8) -> 0.85186275 | I25: =IF(I8=0,0,I24/I8) -> 0.85344045 | J25: =IF(J8=0,0,J24/J8) -> 0.85448916
A27: CUMULATIVE
A28: Cumulative Revenue | B28: =B8 -> 6120 | C28: =B28+C8 -> 18360 | D28: =C28+D8 -> 32232 | E28: =D28+E8 -> 47736 | F28: =E28+F8 -> 64872 | G28: =F28+G8 -> 83640 | H28: =G28+H8 -> 104040 | I28: =H28+I8 -> 126072 | J28: =I28+J8 -> 149328
A29: Cumulative Net Income | B29: =B24 -> 4913 | C29: =B29+C24 -> 15168 | D29: =C29+D24 -> 26848 | E29: =D29+E24 -> 39952 | F29: =E29+F24 -> 54481 | G29: =F29+G24 -> 70435 | H29: =G29+H24 -> 87813 | I29: =H29+I24 -> 106616 | J29: =I29+J24 -> 126488
A30: Annual Run Rate (ARR) | B30: =B8*12 -> 73440 | C30: =C8*12 -> 146880 | D30: =D8*12 -> 166464 | E30: =E8*12 -> 186048 | F30: =F8*12 -> 205632 | G30: =G8*12 -> 225216 | H30: =H8*12 -> 244800 | I30: =I8*12 -> 264384 | J30: =J8*12 -> 279072

Sheet Dashboard
A1: TailWag
A2: Revenue Dashboard | April–December 2026
A5: KEY METRICS | B5: Value
A6: April MRR | B6: ='P&L'!B8 -> 6120
A7: May MRR | B7: ='P&L'!C8 -> 12240
A8: December MRR | B8: ='P&L'!J8 -> 23256
A10: April Clients | B10: =Assumptions!B11 -> 30
A11: May Clients | B11: =Assumptions!C11 -> 60
A12: December Clients | B12: =Assumptions!J11 -> 114
A14: April Net Income | B14: ='P&L'!B24 -> 4913
A15: May Net Income | B15: ='P&L'!C24 -> 10255
A16: December Net Income | B16: ='P&L'!J24 -> 19872
A18: Year-End Cumulative Revenue | B18: ='P&L'!J28 -> 149328
A19: Year-End Cumulative Net Income | B19: ='P&L'!J29 -> 126488
A20: December ARR | B20: ='P&L'!J30 -> 279072
A22: Gross Margin (steady state) | B22: ='P&L'!J14 -> 0.90196078
A23: Net Margin (December) | B23: ='P&L'!J25 -> 0.85448916
A24: Avg Revenue per Client (Dec) | B24: =IF(Assumptions!J11=0,0,'P&L'!J8/Assumptions!J11) -> 204
