Workbook

Sheet Assumptions
A1: TAILWAG RUNWAY & BREAK-EVEN ANALYSIS
A3: INITIAL CONDITIONS
A4: Starting Cash Reserves | B4: 15000
A5: Monthly Operating Expenses | B5: 500
A6: Monthly Revenue (Current) | B6: 687
A8: GROWTH ASSUMPTIONS
A9: Monthly Revenue Growth Rate (%) | B9: 0
A11: KEY OUTPUTS
A12: Current Monthly Burn Rate | B12: =B5-B6 -> -187
A13: Months of Runway (at current burn) | B13: =B4/B12 -> -80.213904
A14: Revenue Needed to Break Even | B14: =B5 -> 500

Sheet Monthly Detail
A1: MONTH-BY-MONTH ANALYSIS
A3: Metric | B3: Mar 26 | C3: Apr 26 | D3: May 26 | E3: Jun 26 | F3: Jul 26 | G3: Aug 26 | H3: Sep 26 | I3: Oct 26 | J3: Nov 26 | K3: Dec 26 | L3: Jan 27 | M3: Feb 27 | N3: Mar 27 | O3: Apr 27 | P3: May 27 | Q3: Jun 27 | R3: Jul 27 | S3: Aug 27 | T3: Sep 27 | U3: Oct 27 | V3: Nov 27 | W3: Dec 27 | X3: Jan 28 | Y3: Feb 28
A4: Opening Cash Balance | B4: =Assumptions!$B$4 -> 15000 | C4: =B8 -> 15187 | D4: =C8 -> 15374 | E4: =D8 -> 15561 | F4: =E8 -> 15748 | G4: =F8 -> 15935 | H4: =G8 -> 16122 | I4: =H8 -> 16309 | J4: =I8 -> 16496 | ... Y4: =X8 -> 19301
A5: Revenue | B5: =Assumptions!$B$6 -> 687 | C5: =B5*(1+Assumptions!$B$9) -> 687 | D5: =C5*(1+Assumptions!$B$9) -> 687 | E5: =D5*(1+Assumptions!$B$9) -> 687 | F5: =E5*(1+Assumptions!$B$9) -> 687 | G5: =F5*(1+Assumptions!$B$9) -> 687 | H5: =G5*(1+Assumptions!$B$9) -> 687 | I5: =H5*(1+Assumptions!$B$9) -> 687 | J5: =I5*(1+Assumptions!$B$9) -> 687 | ... Y5: =X5*(1+Assumptions!$B$9) -> 687
A6: Operating Expenses | B6: =Assumptions!$B$5 -> 500 | C6: =Assumptions!$B$5 -> 500 | D6: =Assumptions!$B$5 -> 500 | E6: =Assumptions!$B$5 -> 500 | F6: =Assumptions!$B$5 -> 500 | G6: =Assumptions!$B$5 -> 500 | H6: =Assumptions!$B$5 -> 500 | I6: =Assumptions!$B$5 -> 500 | ... Y6: =Assumptions!$B$5 -> 500
A7: Net Cash Flow | B7: =B5-B6 -> 187 | C7: =C5-C6 -> 187 | D7: =D5-D6 -> 187 | E7: =E5-E6 -> 187 | F7: =F5-F6 -> 187 | G7: =G5-G6 -> 187 | H7: =H5-H6 -> 187 | I7: =I5-I6 -> 187 | ... Y7: =Y5-Y6 -> 187
A8: Closing Cash Balance | B8: =B4+B7 -> 15187 | C8: =B8+C7 -> 15374 | D8: =C8+D7 -> 15561 | E8: =D8+E7 -> 15748 | F8: =E8+F7 -> 15935 | G8: =F8+G7 -> 16122 | H8: =G8+H7 -> 16309 | I8: =H8+I7 -> 16496 | J8: =I8+J7 -> 16683 | ... Y8: =X8+Y7 -> 19488

Sheet Summary
A1: RUNWAY & BREAK-EVEN SUMMARY
A3: CURRENT STATE
A4: Cash on Hand | B4: =Assumptions!B4 -> 15000
A5: Monthly Revenue | B5: =Assumptions!B6 -> 687
A6: Monthly Expenses | B6: =Assumptions!B5 -> 500
A7: Monthly Burn Rate | B7: =Assumptions!B12 -> -187
A9: RUNWAY ANALYSIS
A10: Months of Runway | B10: =Assumptions!B13 -> -80.213904
A11: Runway Timeline | B11: =TEXT(TODAY() + (B10*30), "mmm d, yyyy") -> Aug 23, 2019
A13: BREAK-EVEN ANALYSIS
A14: Revenue Needed to Break Even | B14: =Assumptions!B14 -> 500
A15: Revenue Gap to Break Even | B15: =B6-B14 -> 0
A16: Revenue Increase Needed (%) | B16: =-B15/B6 -> 0
